[
    {"resultadoPartido": {
        "resultado": {"marcadorPorEquipo": {
            "Argentinos JRS": 3,
            "River Plate": 2
        }},
        "partido": {
            "visitante": {"nombre": "River Plate"},
            "local": {"nombre": "Argentinos JRS"}
        }
    }},
    {"resultadoPartido": {
        "resultado": {"marcadorPorEquipo": {
            "Barracas Central": 1,
            "River Plate": 5
        }},
        "partido": {
            "visitante": {"nombre": "Barracas Central"},
            "local": {"nombre": "River Plate"}
        }
    }},
    {"resultadoPartido": {
        "resultado": {"marcadorPorEquipo": {
            "Velez Sarsfield": 2,
            "River Plate": 0
        }},
        "partido": {
            "visitante": {"nombre": "River Plate"},
            "local": {"nombre": "Velez Sarsfield"}
        }
    }},
    {"resultadoPartido": {
        "resultado": {"marcadorPorEquipo": {
            "Arsenal Sarandi": 1,
            "River Plate": 3
        }},
        "partido": {
            "visitante": {"nombre": "Arsenal Sarandi"},
            "local": {"nombre": "River Plate"}
        }
    }},
    {"resultadoPartido": {
        "resultado": {"marcadorPorEquipo": {
            "Atletico Tucuman": 0,
            "River Plate": 1
        }},
        "partido": {
            "visitante": {"nombre": "Atletico Tucuman"},
            "local": {"nombre": "River Plate"}
        }
    }},
    {"resultadoPartido": {
        "resultado": {"marcadorPorEquipo": {
            "Banfield": 1,
            "River Plate": 1
        }},
        "partido": {
            "visitante": {"nombre": "River Plate"},
            "local": {"nombre": "Banfield"}
        }
    }},
    {"resultadoPartido": {
        "resultado": {"marcadorPorEquipo": {
            "Boca Juniors": 0,
            "River Plate": 2
        }},
        "partido": {
            "visitante": {"nombre": "River Plate"},
            "local": {"nombre": "Boca Juniors"}
        }
    }},
    {"resultadoPartido": {
        "resultado": {"marcadorPorEquipo": {
            "Talleres Cordoba": 0,
            "River Plate": 1
        }},
        "partido": {
            "visitante": {"nombre": "Talleres Cordoba"},
            "local": {"nombre": "River Plate"}
        }
    }},
    {"resultadoPartido": {
        "resultado": {"marcadorPorEquipo": {
            "Colon Santa Fe": 2,
            "River Plate": 2
        }},
        "partido": {
            "visitante": {"nombre": "River Plate"},
            "local": {"nombre": "Colon Santa Fe"}
        }
    }},
    {"resultadoPartido": {
        "resultado": {"marcadorPorEquipo": {
            "Independiente": 0,
            "River Plate": 3
        }},
        "partido": {
            "visitante": {"nombre": "Independiente"},
            "local": {"nombre": "River Plate"}
        }
    }},
    {"resultadoPartido": {
        "resultado": {"marcadorPorEquipo": {
            "Gimnasia L.P.": 1,
            "River Plate": 2
        }},
        "partido": {
            "visitante": {"nombre": "River Plate"},
            "local": {"nombre": "Gimnasia L.P."}
        }
    }},
    {"resultadoPartido": {
        "resultado": {"marcadorPorEquipo": {
            "River Plate": 1,
            "Huracan": 2
        }},
        "partido": {
            "visitante": {"nombre": "Huracan"},
            "local": {"nombre": "River Plate"}
        }
    }},
    {"resultadoPartido": {
        "resultado": {"marcadorPorEquipo": {
            "Rosario Central": 3,
            "River Plate": 1
        }},
        "partido": {
            "visitante": {"nombre": "River Plate"},
            "local": {"nombre": "Rosario Central"}
        }
    }},
    {"resultadoPartido": {
        "resultado": {"marcadorPorEquipo": {
            "Central Cordoba de Santiago": 0,
            "River Plate": 2
        }},
        "partido": {
            "visitante": {"nombre": "River Plate"},
            "local": {"nombre": "Central Cordoba de Santiago"}
        }
    }},
    {"resultadoPartido": {
        "resultado": {"marcadorPorEquipo": {
            "Belgrano Cordoba": 2,
            "River Plate": 1
        }},
        "partido": {
            "visitante": {"nombre": "River Plate"},
            "local": {"nombre": "Belgrano Cordoba"}
        }
    }},
    {"resultadoPartido": {
        "resultado": {"marcadorPorEquipo": {
            "Argentinos JRS": 1,
            "River Plate": 2
        }},
        "partido": {
            "visitante": {"nombre": "Argentinos JRS"},
            "local": {"nombre": "River Plate"}
        }
    }},
    {"resultadoPartido": {
        "resultado": {"marcadorPorEquipo": {
            "Tigre": 0,
            "River Plate": 1
        }},
        "partido": {
            "visitante": {"nombre": "River Plate"},
            "local": {"nombre": "Tigre"}
        }
    }},
    {"resultadoPartido": {
        "resultado": {"marcadorPorEquipo": {
            "Arsenal Sarandi": 2,
            "River Plate": 1
        }},
        "partido": {
            "visitante": {"nombre": "Arsenal Sarandi"},
            "local": {"nombre": "River Plate"}
        }
    }},
    {"resultadoPartido": {
        "resultado": {"marcadorPorEquipo": {
            "Lanus": 0,
            "River Plate": 2
        }},
        "partido": {
            "visitante": {"nombre": "River Plate"},
            "local": {"nombre": "Lanus"}
        }
    }},
    {"resultadoPartido": {
        "resultado": {"marcadorPorEquipo": {
            "River Plate": 3,
            "Godoy Cruz": 0
        }},
        "partido": {
            "visitante": {"nombre": "Godoy Cruz"},
            "local": {"nombre": "River Plate"}
        }
    }},
    {"resultadoPartido": {
        "resultado": {"marcadorPorEquipo": {
            "Union Santa Fe": 0,
            "River Plate": 1
        }},
        "partido": {
            "visitante": {"nombre": "Union Santa Fe"},
            "local": {"nombre": "River Plate"}
        }
    }},
    {"resultadoPartido": {
        "resultado": {"marcadorPorEquipo": {
            "Huracan": 0,
            "River Plate": 3
        }},
        "partido": {
            "visitante": {"nombre": "River Plate"},
            "local": {"nombre": "Huracan"}
        }
    }},
    {"resultadoPartido": {
        "resultado": {"marcadorPorEquipo": {
            "Gimnasia L.P.": 0,
            "River Plate": 3
        }},
        "partido": {
            "visitante": {"nombre": "Gimnasia L.P."},
            "local": {"nombre": "River Plate"}
        }
    }},
    {"resultadoPartido": {
        "resultado": {"marcadorPorEquipo": {
            "Newells Old Boys": 0,
            "River Plate": 1
        }},
        "partido": {
            "visitante": {"nombre": "River Plate"},
            "local": {"nombre": "Newells Old Boys"}
        }
    }},
    {"resultadoPartido": {
        "resultado": {"marcadorPorEquipo": {
            "Independiente": 0,
            "River Plate": 2
        }},
        "partido": {
            "visitante": {"nombre": "Independiente"},
            "local": {"nombre": "River Plate"}
        }
    }},
    {"resultadoPartido": {
        "resultado": {"marcadorPorEquipo": {
            "Atletico Tucuman": 1,
            "River Plate": 1
        }},
        "partido": {
            "visitante": {"nombre": "River Plate"},
            "local": {"nombre": "Atletico Tucuman"}
        }
    }},
    {"resultadoPartido": {
        "resultado": {"marcadorPorEquipo": {
            "Boca Juniors": 0,
            "River Plate": 1
        }},
        "partido": {
            "visitante": {"nombre": "Boca Juniors"},
            "local": {"nombre": "River Plate"}
        }
    }},
    {"resultadoPartido": {
        "resultado": {"marcadorPorEquipo": {
            "Talleres Cordoba": 2,
            "River Plate": 1
        }},
        "partido": {
            "visitante": {"nombre": "River Plate"},
            "local": {"nombre": "Talleres Cordoba"}
        }
    }},
    {"resultadoPartido": {
        "resultado": {"marcadorPorEquipo": {
            "Platense": 1,
            "River Plate": 2
        }},
        "partido": {
            "visitante": {"nombre": "Platense"},
            "local": {"nombre": "River Plate"}
        }
    }},
    {"resultadoPartido": {
        "resultado": {"marcadorPorEquipo": {
            "Velez Sarsfield": 2,
            "River Plate": 2
        }},
        "partido": {
            "visitante": {"nombre": "River Plate"},
            "local": {"nombre": "Velez Sarsfield"}
        }
    }},
    {"resultadoPartido": {
        "resultado": {"marcadorPorEquipo": {
            "Defensa Y Justicia": 0,
            "River Plate": 1
        }},
        "partido": {
            "visitante": {"nombre": "Defensa Y Justicia"},
            "local": {"nombre": "River Plate"}
        }
    }},
    {"resultadoPartido": {
        "resultado": {"marcadorPorEquipo": {
            "Banfield": 1,
            "River Plate": 4
        }},
        "partido": {
            "visitante": {"nombre": "River Plate"},
            "local": {"nombre": "Banfield"}
        }
    }},
    {"resultadoPartido": {
        "resultado": {"marcadorPorEquipo": {
            "Barracas Central": 2,
            "River Plate": 1
        }},
        "partido": {
            "visitante": {"nombre": "River Plate"},
            "local": {"nombre": "Barracas Central"}
        }
    }},
    {"resultadoPartido": {
        "resultado": {"marcadorPorEquipo": {
            "Colon Santa Fe": 0,
            "River Plate": 2
        }},
        "partido": {
            "visitante": {"nombre": "Colon Santa Fe"},
            "local": {"nombre": "River Plate"}
        }
    }},
    {"resultadoPartido": {
        "resultado": {"marcadorPorEquipo": {
            "San Lorenzo": 0,
            "River Plate": 0
        }},
        "partido": {
            "visitante": {"nombre": "River Plate"},
            "local": {"nombre": "San Lorenzo"}
        }
    }},
    {"resultadoPartido": {
        "resultado": {"marcadorPorEquipo": {
            "Estudiantes L.P.": 1,
            "River Plate": 3
        }},
        "partido": {
            "visitante": {"nombre": "Estudiantes L.P."},
            "local": {"nombre": "River Plate"}
        }
    }},
    {"resultadoPartido": {
        "resultado": {"marcadorPorEquipo": {
            "Rosario Central": 3,
            "River Plate": 3
        }},
        "partido": {
            "visitante": {"nombre": "River Plate"},
            "local": {"nombre": "Rosario Central"}
        }
    }},
    {"resultadoPartido": {
        "resultado": {"marcadorPorEquipo": {
            "Racing Club": 1,
            "River Plate": 2
        }},
        "partido": {
            "visitante": {"nombre": "Racing Club"},
            "local": {"nombre": "River Plate"}
        }
    }},
    {"resultadoPartido": {
        "resultado": {"marcadorPorEquipo": {
            "Racing Cordoba": 0,
            "River Plate": 3
        }},
        "partido": {
            "visitante": {"nombre": "Racing Cordoba"},
            "local": {"nombre": "River Plate"}
        }
    }},
    {"resultadoPartido": {
        "resultado": {"marcadorPorEquipo": {
            "Banfield": 2,
            "River Plate": 3
        }},
        "partido": {
            "visitante": {"nombre": "River Plate"},
            "local": {"nombre": "Banfield"}
        }
    }},
    {"resultadoPartido": {
        "resultado": {"marcadorPorEquipo": {
            "Monterrey": 0,
            "River Plate": 1
        }},
        "partido": {
            "visitante": {"nombre": "Monterrey"},
            "local": {"nombre": "River Plate"}
        }
    }},
    {"resultadoPartido": {
        "resultado": {"marcadorPorEquipo": {
            "Colon Santa Fe": 2,
            "River Plate": 1
        }},
        "partido": {
            "visitante": {"nombre": "River Plate"},
            "local": {"nombre": "Colon Santa Fe"}
        }
    }},
    {"resultadoPartido": {
        "resultado": {"marcadorPorEquipo": {
            "Millonarios": 0,
            "River Plate": 2
        }},
        "partido": {
            "visitante": {"nombre": "Millonarios"},
            "local": {"nombre": "River Plate"}
        }
    }},
    {"resultadoPartido": {
        "resultado": {"marcadorPorEquipo": {
            "Vasco DA Gama": 0,
            "River Plate": 3
        }},
        "partido": {
            "visitante": {"nombre": "Vasco DA Gama"},
            "local": {"nombre": "River Plate"}
        }
    }},
    {"resultadoPartido": {
        "resultado": {"marcadorPorEquipo": {
            "Sarmiento Junin": 0,
            "River Plate": 2
        }},
        "partido": {
            "visitante": {"nombre": "River Plate"},
            "local": {"nombre": "Sarmiento Junin"}
        }
    }},
    {"resultadoPartido": {
        "resultado": {"marcadorPorEquipo": {
            "Instituto Cordoba": 1,
            "River Plate": 3
        }},
        "partido": {
            "visitante": {"nombre": "Instituto Cordoba"},
            "local": {"nombre": "River Plate"}
        }
    }},
    {"resultadoPartido": {
        "resultado": {"marcadorPorEquipo": {
            "River Plate": 1,
            "Boston River": 0
        }},
        "partido": {
            "visitante": {"nombre": "Boston River"},
            "local": {"nombre": "River Plate"}
        }
    }},
    {"resultadoPartido": {
        "resultado": {"marcadorPorEquipo": {
            "Universidad de Chile": 3,
            "River Plate": 4
        }},
        "partido": {
            "visitante": {"nombre": "Universidad de Chile"},
            "local": {"nombre": "River Plate"}
        }
    }},
    {"resultadoPartido": {
        "resultado": {"marcadorPorEquipo": {
            "The Strongest": 3,
            "River Plate": 1
        }},
        "partido": {
            "visitante": {"nombre": "River Plate"},
            "local": {"nombre": "The Strongest"}
        }
    }},
    {"resultadoPartido": {
        "resultado": {"marcadorPorEquipo": {
            "Sporting Cristal": 2,
            "River Plate": 4
        }},
        "partido": {
            "visitante": {"nombre": "Sporting Cristal"},
            "local": {"nombre": "River Plate"}
        }
    }},
    {"resultadoPartido": {
        "resultado": {"marcadorPorEquipo": {
            "Fluminense": 5,
            "River Plate": 1
        }},
        "partido": {
            "visitante": {"nombre": "River Plate"},
            "local": {"nombre": "Fluminense"}
        }
    }},
    {"resultadoPartido": {
        "resultado": {"marcadorPorEquipo": {
            "Sporting Cristal": 1,
            "River Plate": 1
        }},
        "partido": {
            "visitante": {"nombre": "River Plate"},
            "local": {"nombre": "Sporting Cristal"}
        }
    }},
    {"resultadoPartido": {
        "resultado": {"marcadorPorEquipo": {
            "Fluminense": 0,
            "River Plate": 2
        }},
        "partido": {
            "visitante": {"nombre": "Fluminense"},
            "local": {"nombre": "River Plate"}
        }
    }},
    {"resultadoPartido": {
        "resultado": {"marcadorPorEquipo": {
            "The Strongest": 0,
            "River Plate": 2
        }},
        "partido": {
            "visitante": {"nombre": "The Strongest"},
            "local": {"nombre": "River Plate"}
        }
    }},
    {"resultadoPartido": {
        "resultado": {"marcadorPorEquipo": {
            "Talleres Cordoba": 1,
            "River Plate": 0
        }},
        "partido": {
            "visitante": {"nombre": "Talleres Cordoba"},
            "local": {"nombre": "River Plate"}
        }
    }},
    {"resultadoPartido": {
        "resultado": {"marcadorPorEquipo": {
            "Internacional": 1,
            "River Plate": 2
        }},
        "partido": {
            "visitante": {"nombre": "Internacional"},
            "local": {"nombre": "River Plate"}
        }
    }},
    {"resultadoPartido": {
        "resultado": {"marcadorPorEquipo": {
            "Internacional": 2,
            "River Plate": 1
        }},
        "partido": {
            "visitante": {"nombre": "River Plate"},
            "local": {"nombre": "Internacional"}
        }
    }},
    {"resultadoPartido": {
        "resultado": {"marcadorPorEquipo": {
            "U. Catolica": 0,
            "River Plate": 1
        }},
        "partido": {
            "visitante": {"nombre": "U. Catolica"},
            "local": {"nombre": "River Plate"}
        }
    }}
]